steam_client/__init__.py
steam_client/app.py
steam_client/commands.py
steam_client/game.py
steam_client/library.py
steam_client/library_directory.py
steam_client/login_users.py
steam_client/py.typed
steam_client/shortcut.py
steam_client/steam.py
steam_client/utils.py
steam_client/web_api.py
steam_client-2.1.0.dev0.dist-info/LICENSE
steam_client-2.1.0.dev0.dist-info/METADATA
steam_client-2.1.0.dev0.dist-info/WHEEL
steam_client-2.1.0.dev0.dist-info/top_level.txt
steam_client-2.1.0.dev0.dist-info/RECORD
